{"meta.json":"0.36.0:G9PDY8XLQ2eyB90BoXcxFQ","battleEnvironments.json":"0.36.0:G9PDY8XLQ2eyB90BoXcxFQ","xpTable.json":"0.36.0:G9PDY8XLQ2eyB90BoXcxFQ","material.json":"0.36.0:G9PDY8XLQ2eyB90BoXcxFQ","category.json":"0.36.0:G9PDY8XLQ2eyB90BoXcxFQ","skill.json":"0.36.0:G9PDY8XLQ2eyB90BoXcxFQ","eventSampling.json":"0.36.0:G9PDY8XLQ2eyB90BoXcxFQ","equipment.json":"0.36.0:G9PDY8XLQ2eyB90BoXcxFQ","targetingSet.json":"0.36.0:G9PDY8XLQ2eyB90BoXcxFQ","effect.json":"0.36.0:G9PDY8XLQ2eyB90BoXcxFQ","requirement.json":"0.36.0:G9PDY8XLQ2eyB90BoXcxFQ","powerUpBundle.json":"0.36.0:G9PDY8XLQ2eyB90BoXcxFQ","table.json":"0.36.0:G9PDY8XLQ2eyB90BoXcxFQ","unlockAnnouncementDefinition.json":"0.36.0:G9PDY8XLQ2eyB90BoXcxFQ","battleTargetingRule.json":"0.36.0:G9PDY8XLQ2eyB90BoXcxFQ","environmentCollection.json":"0.36.0:G9PDY8XLQ2eyB90BoXcxFQ","playerTitle.json":"0.36.0:G9PDY8XLQ2eyB90BoXcxFQ","persistentVfx.json":"0.36.0:G9PDY8XLQ2eyB90BoXcxFQ","playerPortrait.json":"0.36.0:G9PDY8XLQ2eyB90BoXcxFQ","effectIconPriority.json":"0.36.0:G9PDY8XLQ2eyB90BoXcxFQ","guildBanner.json":"0.36.0:G9PDY8XLQ2eyB90BoXcxFQ","socialStatus.json":"0.36.0:G9PDY8XLQ2eyB90BoXcxFQ","timeZoneChangeConfig.json":"0.36.0:G9PDY8XLQ2eyB90BoXcxFQ","recipe.json":"0.36.0:G9PDY8XLQ2eyB90BoXcxFQ","statProgression.json":"0.36.0:G9PDY8XLQ2eyB90BoXcxFQ","challenge.json":"0.36.0:G9PDY8XLQ2eyB90BoXcxFQ","warDefinition.json":"0.36.0:G9PDY8XLQ2eyB90BoXcxFQ","ability.json":"0.36.0:G9PDY8XLQ2eyB90BoXcxFQ","raidConfig.json":"0.36.0:G9PDY8XLQ2eyB90BoXcxFQ","guildRaid.json":"0.36.0:G9PDY8XLQ2eyB90BoXcxFQ","statModSet.json":"0.36.0:G9PDY8XLQ2eyB90BoXcxFQ","statMod.json":"0.36.0:G9PDY8XLQ2eyB90BoXcxFQ","guildExchangeItem.json":"0.36.0:G9PDY8XLQ2eyB90BoXcxFQ","territoryBattleDefinition.json":"0.36.0:G9PDY8XLQ2eyB90BoXcxFQ","territoryWarDefinition.json":"0.36.0:G9PDY8XLQ2eyB90BoXcxFQ","challengeStyle.json":"0.36.0:G9PDY8XLQ2eyB90BoXcxFQ","starterGuild.json":"0.36.0:G9PDY8XLQ2eyB90BoXcxFQ","modRecommendation.json":"0.36.0:G9PDY8XLQ2eyB90BoXcxFQ","territoryTournamentDefinition.json":"0.36.0:G9PDY8XLQ2eyB90BoXcxFQ","seasonDefinition.json":"0.36.0:G9PDY8XLQ2eyB90BoXcxFQ","mysteryBox.json":"0.36.0:G9PDY8XLQ2eyB90BoXcxFQ","mysteryStatMod.json":"0.36.0:G9PDY8XLQ2eyB90BoXcxFQ","cooldown.json":"0.36.0:G9PDY8XLQ2eyB90BoXcxFQ","dailyActionCap.json":"0.36.0:G9PDY8XLQ2eyB90BoXcxFQ","energyReward.json":"0.36.0:G9PDY8XLQ2eyB90BoXcxFQ","seasonLeagueDefinition.json":"0.36.0:G9PDY8XLQ2eyB90BoXcxFQ","seasonDivisionDefinition.json":"0.36.0:G9PDY8XLQ2eyB90BoXcxFQ","seasonRewardTable.json":"0.36.0:G9PDY8XLQ2eyB90BoXcxFQ","scavengerConversionSet.json":"0.36.0:G9PDY8XLQ2eyB90BoXcxFQ","unitGuideDefinition.json":"0.36.0:G9PDY8XLQ2eyB90BoXcxFQ","galacticBundle.json":"0.36.0:G9PDY8XLQ2eyB90BoXcxFQ","linkedStoreItem.json":"0.36.0:G9PDY8XLQ2eyB90BoXcxFQ","territoryTournamentLeagueDefinition.json":"0.36.0:G9PDY8XLQ2eyB90BoXcxFQ","territoryTournamentDivisionDefinition.json":"0.36.0:G9PDY8XLQ2eyB90BoXcxFQ","savedSquadConfig.json":"0.36.0:G9PDY8XLQ2eyB90BoXcxFQ","guildRaidGlobalConfig.json":"0.36.0:G9PDY8XLQ2eyB90BoXcxFQ","units.json":"0.36.0:G9PDY8XLQ2eyB90BoXcxFQ","units_pve.json":"0.36.0:G9PDY8XLQ2eyB90BoXcxFQ","units_gas":"0.36.0:G9PDY8XLQ2eyB90BoXcxFQ","relicTierDefinition.json":"0.36.0:G9PDY8XLQ2eyB90BoXcxFQ","campaign.json":"0.36.0:G9PDY8XLQ2eyB90BoXcxFQ","conquestDefinition.json":"0.36.0:G9PDY8XLQ2eyB90BoXcxFQ","conquestMission.json":"0.36.0:G9PDY8XLQ2eyB90BoXcxFQ","artifactDefinition.json":"0.36.0:G9PDY8XLQ2eyB90BoXcxFQ","consumableDefinition.json":"0.36.0:G9PDY8XLQ2eyB90BoXcxFQ","consumableType.json":"0.36.0:G9PDY8XLQ2eyB90BoXcxFQ","artifactTierDefinition.json":"0.36.0:G9PDY8XLQ2eyB90BoXcxFQ","consumableTierDefinition.json":"0.36.0:G9PDY8XLQ2eyB90BoXcxFQ","recommendedSquad.json":"0.36.0:G9PDY8XLQ2eyB90BoXcxFQ","unitGuideLayout.json":"0.36.0:G9PDY8XLQ2eyB90BoXcxFQ","dailyLoginRewardDefinition.json":"0.36.0:G9PDY8XLQ2eyB90BoXcxFQ","calendarCategoryDefinition.json":"0.36.0:G9PDY8XLQ2eyB90BoXcxFQ","datacronSet.json":"0.36.0:G9PDY8XLQ2eyB90BoXcxFQ","datacronTemplate.json":"0.36.0:G9PDY8XLQ2eyB90BoXcxFQ","datacronAffixTemplateSet.json":"0.36.0:G9PDY8XLQ2eyB90BoXcxFQ","datacronHelpEntry.json":"0.36.0:G9PDY8XLQ2eyB90BoXcxFQ","displayableEnemy.json":"0.36.0:G9PDY8XLQ2eyB90BoXcxFQ","episodeDefinition.json":"0.36.0:G9PDY8XLQ2eyB90BoXcxFQ","territoryTournamentDailyRewardTable.json":"0.36.0:G9PDY8XLQ2eyB90BoXcxFQ","linkingReward.json":"0.36.0:G9PDY8XLQ2eyB90BoXcxFQ","enums.json":"0.36.0:G9PDY8XLQ2eyB90BoXcxFQ","Loc_CHS_CN.txt.json":"IJRQe55sQC2it9KwCydNAw","Loc_CHT_CN.txt.json":"IJRQe55sQC2it9KwCydNAw","Loc_ENG_US.txt.json":"IJRQe55sQC2it9KwCydNAw","Loc_FRE_FR.txt.json":"IJRQe55sQC2it9KwCydNAw","Loc_GER_DE.txt.json":"IJRQe55sQC2it9KwCydNAw","Loc_IND_ID.txt.json":"IJRQe55sQC2it9KwCydNAw","Loc_ITA_IT.txt.json":"IJRQe55sQC2it9KwCydNAw","Loc_JPN_JP.txt.json":"IJRQe55sQC2it9KwCydNAw","Loc_Key_Mapping.txt.json":"IJRQe55sQC2it9KwCydNAw","Loc_KOR_KR.txt.json":"IJRQe55sQC2it9KwCydNAw","Loc_POR_BR.txt.json":"IJRQe55sQC2it9KwCydNAw","Loc_RUS_RU.txt.json":"IJRQe55sQC2it9KwCydNAw","Loc_SPA_XM.txt.json":"IJRQe55sQC2it9KwCydNAw","Loc_THA_TH.txt.json":"IJRQe55sQC2it9KwCydNAw","Loc_TUR_TR.txt.json":"IJRQe55sQC2it9KwCydNAw","gameData.json":"0.36.0:G9PDY8XLQ2eyB90BoXcxFQ","gameVersion":"0.36.0:G9PDY8XLQ2eyB90BoXcxFQ","localeVersion":"IJRQe55sQC2it9KwCydNAw","assetVersion":3605}