{"enums.json":"0.31.5:YPBmJn7MQbaCHQ745GhO2w","units.json":"0.31.5:YPBmJn7MQbaCHQ745GhO2w","units_pve.json":"0.31.5:YPBmJn7MQbaCHQ745GhO2w","battleEnvironments.json":"0.31.5:YPBmJn7MQbaCHQ745GhO2w","xpTable.json":"0.31.5:YPBmJn7MQbaCHQ745GhO2w","material.json":"0.31.5:YPBmJn7MQbaCHQ745GhO2w","recipe.json":"0.31.5:YPBmJn7MQbaCHQ745GhO2w","statProgression.json":"0.31.5:YPBmJn7MQbaCHQ745GhO2w","category.json":"0.31.5:YPBmJn7MQbaCHQ745GhO2w","helpEntry.json":"0.31.5:YPBmJn7MQbaCHQ745GhO2w","challenge.json":"0.31.5:YPBmJn7MQbaCHQ745GhO2w","skill.json":"0.31.5:YPBmJn7MQbaCHQ745GhO2w","eventSampling.json":"0.31.5:YPBmJn7MQbaCHQ745GhO2w","equipment.json":"0.31.5:YPBmJn7MQbaCHQ745GhO2w","warDefinition.json":"0.31.5:YPBmJn7MQbaCHQ745GhO2w","targetingSet.json":"0.31.5:YPBmJn7MQbaCHQ745GhO2w","ability.json":"0.31.5:YPBmJn7MQbaCHQ745GhO2w","effect.json":"0.31.5:YPBmJn7MQbaCHQ745GhO2w","requirement.json":"0.31.5:YPBmJn7MQbaCHQ745GhO2w","powerUpBundle.json":"0.31.5:YPBmJn7MQbaCHQ745GhO2w","raidConfig.json":"0.31.5:YPBmJn7MQbaCHQ745GhO2w","guildRaid.json":"0.31.5:YPBmJn7MQbaCHQ745GhO2w","statModSet.json":"0.31.5:YPBmJn7MQbaCHQ745GhO2w","statMod.json":"0.31.5:YPBmJn7MQbaCHQ745GhO2w","guildExchangeItem.json":"0.31.5:YPBmJn7MQbaCHQ745GhO2w","table.json":"0.31.5:YPBmJn7MQbaCHQ745GhO2w","unlockAnnouncementDefinition.json":"0.31.5:YPBmJn7MQbaCHQ745GhO2w","battleTargetingRule.json":"0.31.5:YPBmJn7MQbaCHQ745GhO2w","territoryBattleDefinition.json":"0.31.5:YPBmJn7MQbaCHQ745GhO2w","territoryWarDefinition.json":"0.31.5:YPBmJn7MQbaCHQ745GhO2w","environmentCollection.json":"0.31.5:YPBmJn7MQbaCHQ745GhO2w","challengeStyle.json":"0.31.5:YPBmJn7MQbaCHQ745GhO2w","starterGuild.json":"0.31.5:YPBmJn7MQbaCHQ745GhO2w","playerTitle.json":"0.31.5:YPBmJn7MQbaCHQ745GhO2w","modRecommendation.json":"0.31.5:YPBmJn7MQbaCHQ745GhO2w","persistentVfx.json":"0.31.5:YPBmJn7MQbaCHQ745GhO2w","territoryTournamentDefinition.json":"0.31.5:YPBmJn7MQbaCHQ745GhO2w","seasonDefinition.json":"0.31.5:YPBmJn7MQbaCHQ745GhO2w","playerPortrait.json":"0.31.5:YPBmJn7MQbaCHQ745GhO2w","effectIconPriority.json":"0.31.5:YPBmJn7MQbaCHQ745GhO2w","mysteryBox.json":"0.31.5:YPBmJn7MQbaCHQ745GhO2w","mysteryStatMod.json":"0.31.5:YPBmJn7MQbaCHQ745GhO2w","cooldown.json":"0.31.5:YPBmJn7MQbaCHQ745GhO2w","dailyActionCap.json":"0.31.5:YPBmJn7MQbaCHQ745GhO2w","energyReward.json":"0.31.5:YPBmJn7MQbaCHQ745GhO2w","seasonLeagueDefinition.json":"0.31.5:YPBmJn7MQbaCHQ745GhO2w","seasonDivisionDefinition.json":"0.31.5:YPBmJn7MQbaCHQ745GhO2w","seasonRewardTable.json":"0.31.5:YPBmJn7MQbaCHQ745GhO2w","relicTierDefinition.json":"0.31.5:YPBmJn7MQbaCHQ745GhO2w","scavengerConversionSet.json":"0.31.5:YPBmJn7MQbaCHQ745GhO2w","unitGuideDefinition.json":"0.31.5:YPBmJn7MQbaCHQ745GhO2w","galacticBundle.json":"0.31.5:YPBmJn7MQbaCHQ745GhO2w","linkedStoreItem.json":"0.31.5:YPBmJn7MQbaCHQ745GhO2w","territoryTournamentLeagueDefinition.json":"0.31.5:YPBmJn7MQbaCHQ745GhO2w","territoryTournamentDivisionDefinition.json":"0.31.5:YPBmJn7MQbaCHQ745GhO2w","savedSquadConfig.json":"0.31.5:YPBmJn7MQbaCHQ745GhO2w","campaign.json":"0.31.5:YPBmJn7MQbaCHQ745GhO2w","conquestDefinition.json":"0.31.5:YPBmJn7MQbaCHQ745GhO2w","conquestMission.json":"0.31.5:YPBmJn7MQbaCHQ745GhO2w","artifactDefinition.json":"0.31.5:YPBmJn7MQbaCHQ745GhO2w","consumableDefinition.json":"0.31.5:YPBmJn7MQbaCHQ745GhO2w","consumableType.json":"0.31.5:YPBmJn7MQbaCHQ745GhO2w","artifactTierDefinition.json":"0.31.5:YPBmJn7MQbaCHQ745GhO2w","consumableTierDefinition.json":"0.31.5:YPBmJn7MQbaCHQ745GhO2w","recommendedSquad.json":"0.31.5:YPBmJn7MQbaCHQ745GhO2w","unitGuideLayout.json":"0.31.5:YPBmJn7MQbaCHQ745GhO2w","dailyLoginRewardDefinition.json":"0.31.5:YPBmJn7MQbaCHQ745GhO2w","calendarCategoryDefinition.json":"0.31.5:YPBmJn7MQbaCHQ745GhO2w","datacronSet.json":"0.31.5:YPBmJn7MQbaCHQ745GhO2w","datacronTemplate.json":"0.31.5:YPBmJn7MQbaCHQ745GhO2w","datacronAffixTemplateSet.json":"0.31.5:YPBmJn7MQbaCHQ745GhO2w","datacronHelpEntry.json":"0.31.5:YPBmJn7MQbaCHQ745GhO2w","territoryTournamentMatchmakingDescKey.json":"0.31.5:YPBmJn7MQbaCHQ745GhO2w","gameData.json":"0.31.5:YPBmJn7MQbaCHQ745GhO2w","Loc_CHS_CN.txt.json":"yqHxd287TtSL1w5xFitiig","Loc_CHT_CN.txt.json":"yqHxd287TtSL1w5xFitiig","Loc_ENG_US.txt.json":"yqHxd287TtSL1w5xFitiig","Loc_FRE_FR.txt.json":"yqHxd287TtSL1w5xFitiig","Loc_GER_DE.txt.json":"yqHxd287TtSL1w5xFitiig","Loc_IND_ID.txt.json":"yqHxd287TtSL1w5xFitiig","Loc_ITA_IT.txt.json":"yqHxd287TtSL1w5xFitiig","Loc_JPN_JP.txt.json":"yqHxd287TtSL1w5xFitiig","Loc_Key_Mapping.txt.json":"yqHxd287TtSL1w5xFitiig","Loc_KOR_KR.txt.json":"yqHxd287TtSL1w5xFitiig","Loc_POR_BR.txt.json":"yqHxd287TtSL1w5xFitiig","Loc_RUS_RU.txt.json":"yqHxd287TtSL1w5xFitiig","Loc_SPA_XM.txt.json":"yqHxd287TtSL1w5xFitiig","Loc_THA_TH.txt.json":"yqHxd287TtSL1w5xFitiig","Loc_TUR_TR.txt.json":"yqHxd287TtSL1w5xFitiig","gameVersion":"0.31.5:YPBmJn7MQbaCHQ745GhO2w","localeVersion":"yqHxd287TtSL1w5xFitiig"}